src/control_unit.vhd
-- fpga4student.com: FPGA projects, Verilog projects, VHDL projects
-- VHDL project: VHDL code for single-cycle MIPS Processor
library IEEE;
use IEEE.STD_LOGIC_1164.ALL;
-- VHDL code for Control Unit of the MIPS Processor
entity control_unit_VHDL is
port (
  opcode: in std_logic_vector(5 downto 0);
  reset: in std_logic;
  reg_dst,mem_to_reg,alu_op: out std_logic_vector(1 downto 0);
  jump,branch,mem_read,mem_write,alu_src,reg_write,sign_or_zero: out std_logic
 );
end control_unit_VHDL;

architecture Behavioral of control_unit_VHDL is

begin
process(reset,opcode)
begin
 if(reset = '1') then
   reg_dst <= "00";
   mem_to_reg <= "00";
   alu_op <= "00";
   jump <= '0';
   branch <= '0';
   mem_read <= '0';
   mem_write <= '0';
   alu_src <= '0';
   reg_write <= '0';
   sign_or_zero <= '1';
 else 
  case opcode is
    when "000000" => -- R
      reg_dst <= "01";
      mem_to_reg <= "00";
      alu_op <= "00";
      jump <= '0';
      branch <= '0';
      mem_read <= '0';
      mem_write <= '0';
      alu_src <= '0';
      reg_write <= '1';
      sign_or_zero <= '1';
    when "000001" => -- sliu
      reg_dst <= "00";
      mem_to_reg <= "00";
      alu_op <= "10";
      jump <= '0';
      branch <= '0';
      mem_read <= '0';
      mem_write <= '0';
      alu_src <= '1';
      reg_write <= '1';
      sign_or_zero <= '0';
    when "000010" => -- j
      reg_dst <= "00";
      mem_to_reg <= "00";
      alu_op <= "00";
      jump <= '1';
      branch <= '0';
      mem_read <= '0';
      mem_write <= '0';
      alu_src <= '0';
      reg_write <= '0';
      sign_or_zero <= '1';
    when "000011" =>-- jal
      reg_dst <= "10";
      mem_to_reg <= "10";
      alu_op <= "00";
      jump <= '1';
      branch <=  '0';
      mem_read <=  '0';
      mem_write <=  '0';
      alu_src <= '0';
      reg_write <=  '1';
      sign_or_zero <= '1';
    when "010011" =>-- lw
      reg_dst <= "00";
      mem_to_reg <= "01";
      alu_op <= "11";
      jump <= '0';
      branch <= '0';
      mem_read <= '1';
      mem_write <= '0';
      alu_src <= '1';
      reg_write <= '1';
      sign_or_zero <= '1';
    when "101011" => -- sw
      reg_dst <= "00";
      mem_to_reg <= "00";
      alu_op <= "11";
      jump <= '0';
      branch <= '0';
      mem_read <= '0';
      mem_write <= '1';
      alu_src <= '1';
      reg_write <= '0';
      sign_or_zero <= '1';
    when "000100" => -- beq
      reg_dst <= "00";
      mem_to_reg <= "00";
      alu_op <= "01";
      jump <= '0';
      branch <= '1';
      mem_read <= '0';
      mem_write <= '0';
      alu_src <= '0';
      reg_write <= '0';
      sign_or_zero <= '1';
    when "100000" =>-- addi
      reg_dst <= "00";
      mem_to_reg <= "00";
      alu_op <= "11";
      jump <= '0';
      branch <= '0';
      mem_read <= '0';
      mem_write <= '0';
      alu_src <= '1';
      reg_write <= '1';
      sign_or_zero <= '1';
    when "100001" =>-- addfi
      reg_dst <= "00";
      mem_to_reg <= "00";
      alu_op <= "11";
      jump <= '0';
      branch <= '0';
      mem_read <= '0';
      mem_write <= '0';
      alu_src <= '1';
      reg_write <= '1';
      sign_or_zero <= '1';
    when "100010" =>-- subi
      reg_dst <= "00";
      mem_to_reg <= "00";
      alu_op <= "11";
      jump <= '0';
      branch <= '0';
      mem_read <= '0';
      mem_write <= '0';
      alu_src <= '1';
      reg_write <= '1';
      sign_or_zero <= '1';
    when "100011" =>-- subfi
      reg_dst <= "00";
      mem_to_reg <= "00";
      alu_op <= "11";
      jump <= '0';
      branch <= '0';
      mem_read <= '0';
      mem_write <= '0';
      alu_src <= '1';
      reg_write <= '1';
      sign_or_zero <= '1';
    when "100100" =>-- andi
      reg_dst <= "00";
      mem_to_reg <= "00";
      alu_op <= "11";
      jump <= '0';
      branch <= '0';
      mem_read <= '0';
      mem_write <= '0';
      alu_src <= '1';
      reg_write <= '1';
      sign_or_zero <= '1';
    when "100101" =>-- ori
      reg_dst <= "00";
      mem_to_reg <= "00";
      alu_op <= "11";
      jump <= '0';
      branch <= '0';
      mem_read <= '0';
      mem_write <= '0';
      alu_src <= '1';
      reg_write <= '1';
      sign_or_zero <= '1';
    when others =>   
      reg_dst <= "01";
      mem_to_reg <= "00";
      alu_op <= "00";
      jump <= '0';
      branch <= '0';
      mem_read <= '0';
      mem_write <= '0';
      alu_src <= '0';
      reg_write <= '1';
      sign_or_zero <= '1';
  end case;
 end if;
end process;

end Behavioral;

tb/tb_control_unit.vhd
library ieee;
use ieee.std_logic_1164.all;
use ieee.numeric_std.all;

entity tb_control_unit is
end entity;

architecture behavioral of tb_control_unit is

  component control_unit_VHDL
    port (
      opcode        : in  std_logic_vector(5 downto 0);
      reset         : in  std_logic;
      reg_dst       : out std_logic_vector(1 downto 0);
      mem_to_reg    : out std_logic_vector(1 downto 0);
      alu_op        : out std_logic_vector(1 downto 0);
      jump          : out std_logic;
      branch        : out std_logic;
      mem_read      : out std_logic;
      mem_write     : out std_logic;
      alu_src       : out std_logic;
      reg_write     : out std_logic;
      sign_or_zero  : out std_logic
    );
  end component;

  -- signals
  signal opcode        : std_logic_vector(5 downto 0) := (others => '0');
  signal reset         : std_logic := '1';
  signal reg_dst       : std_logic_vector(1 downto 0);
  signal mem_to_reg    : std_logic_vector(1 downto 0);
  signal alu_op        : std_logic_vector(1 downto 0);
  signal jump          : std_logic;
  signal branch        : std_logic;
  signal mem_read      : std_logic;
  signal mem_write     : std_logic;
  signal alu_src       : std_logic;
  signal reg_write     : std_logic;
  signal sign_or_zero  : std_logic;

  -- Função: slv -> string
  function slv_to_string(slv: std_logic_vector) return string is
    variable s : string(1 to slv'length);
  begin
    for i in slv'range loop
      s(i - slv'low + 1) := character'value(std_logic'image(slv(i)));
    end loop;
    return s;
  end function;

begin

  uut: control_unit_VHDL
    port map(
      opcode       => opcode,
      reset        => reset,
      reg_dst      => reg_dst,
      mem_to_reg   => mem_to_reg,
      alu_op       => alu_op,
      jump         => jump,
      branch       => branch,
      mem_read     => mem_read,
      mem_write    => mem_write,
      alu_src      => alu_src,
      reg_write    => reg_write,
      sign_or_zero => sign_or_zero
    );

  stim_proc: process

    procedure test_opcode(code: std_logic_vector(5 downto 0); name: string) is
    begin
      opcode <= code;
      wait for 10 ns;

      report "=== Testing " & name &
             " | opcode=" & slv_to_string(code) &
             " | reg_dst=" & slv_to_string(reg_dst) &
             " | mem_to_reg=" & slv_to_string(mem_to_reg) &
             " | alu_op=" & slv_to_string(alu_op) &
             " | jump=" & std_logic'image(jump) &
             " | branch=" & std_logic'image(branch) &
             " | mem_read=" & std_logic'image(mem_read) &
             " | mem_write=" & std_logic'image(mem_write) &
             " | alu_src=" & std_logic'image(alu_src) &
             " | reg_write=" & std_logic'image(reg_write) &
             " | sign_or_zero=" & std_logic'image(sign_or_zero);
    end procedure;

  begin

    reset <= '1';
    wait for 10 ns;
    reset <= '0';
    wait for 10 ns;

    test_opcode("000000", "R-type");
    test_opcode("000001", "sliu");
    test_opcode("000010", "j");
    test_opcode("000011", "jal");
    test_opcode("010011", "lw");
    test_opcode("101011", "sw");
    test_opcode("000100", "beq");
    test_opcode("100000", "addi");
    test_opcode("100001", "addfi");
    test_opcode("100010", "subi");
    test_opcode("100011", "subfi");
    test_opcode("100100", "andi");
    test_opcode("100101", "ori");

    test_opcode("111111", "default");

    wait;
  end process;

end architecture behavioral;

sim/control_unit.vcd
$date
  Sun Nov 16 18:40:13 2025
$end
$version
  GHDL v0
$end
$timescale
  1 fs
$end
$scope module standard $end
$upscope $end
$scope module textio $end
$upscope $end
$scope module std_logic_1164 $end
$upscope $end
$scope module numeric_std $end
$upscope $end
$scope module tb_control_unit $end
$var reg 6 ! opcode[5:0] $end
$var reg 1 " reset $end
$var reg 2 # reg_dst[1:0] $end
$var reg 2 $ mem_to_reg[1:0] $end
$var reg 2 % alu_op[1:0] $end
$var reg 1 & jump $end
$var reg 1 ' branch $end
$var reg 1 ( mem_read $end
$var reg 1 ) mem_write $end
$var reg 1 * alu_src $end
$var reg 1 + reg_write $end
$var reg 1 , sign_or_zero $end
$scope module uut $end
$var reg 6 - opcode[5:0] $end
$var reg 1 . reset $end
$var reg 2 / reg_dst[1:0] $end
$var reg 2 0 mem_to_reg[1:0] $end
$var reg 2 1 alu_op[1:0] $end
$var reg 1 2 jump $end
$var reg 1 3 branch $end
$var reg 1 4 mem_read $end
$var reg 1 5 mem_write $end
$var reg 1 6 alu_src $end
$var reg 1 7 reg_write $end
$var reg 1 8 sign_or_zero $end
$upscope $end
$upscope $end
$enddefinitions $end
#0
b000000 !
1"
b00 #
b00 $
b00 %
0&
0'
0(
0)
0*
0+
1,
b000000 -
1.
b00 /
b00 0
b00 1
02
03
04
05
06
07
18
#10000000
0"
b01 #
1+
0.
b01 /
17
#20000000
#30000000
b000001 !
b00 #
b10 %
1*
0,
b000001 -
b00 /
b10 1
16
08
#40000000
b000010 !
b00 %
1&
0*
0+
1,
b000010 -
b00 1
12
06
07
18
#50000000
b000011 !
b10 #
b10 $
1+
b000011 -
b10 /
b10 0
17
#60000000
b010011 !
b00 #
b01 $
b11 %
0&
1(
1*
b010011 -
b00 /
b01 0
b11 1
02
14
16
#70000000
b101011 !
b00 $
0(
1)
0+
b101011 -
b00 0
04
15
07
#80000000
b000100 !
b01 %
1'
0)
0*
b000100 -
b01 1
13
05
06
#90000000
b100000 !
b11 %
0'
1*
1+
b100000 -
b11 1
03
16
17
#100000000
b100001 !
b100001 -
#110000000
b100010 !
b100010 -
#120000000
b100011 !
b100011 -
#130000000
b100100 !
b100100 -
#140000000
b100101 !
b100101 -
#150000000
b111111 !
b01 #
b00 %
0*
b111111 -
b01 /
b00 1
06
