src/instruction_memory.vhd
library ieee;
use ieee.std_logic_1164.all;
use ieee.numeric_std.all;
use std.textio.all;
use ieee.std_logic_textio.all;

entity Instruction_Memory is
    port (
        clk        : in  std_logic;
        pc         : in  std_logic_vector(31 downto 0);
        instruction: out std_logic_vector(31 downto 0)
    );
end Instruction_Memory;

architecture behavioral of Instruction_Memory is

    type memory_type is array(0 to 255) of std_logic_vector(31 downto 0);
    signal mem : memory_type := (others => (others => '0'));

begin

    -- Leitura combinacional baseada no PC
    instruction <= mem(to_integer(unsigned(pc(9 downto 2))));

    ----------------------------------------------------------------
    -- Inicialização da memória a partir do arquivo .input
    ----------------------------------------------------------------
    load_memory: process
        file f : text open read_mode is "tests/instruction.input";
        variable line_v : line;
        variable instr_v : std_logic_vector(31 downto 0);
        variable addr : integer := 0;
    begin
        wait for 10 ns;  -- tempo inicial para simulação
        while not endfile(f) loop
            readline(f, line_v);
            hread(line_v, instr_v);  -- lê instrução em hexadecimal
            mem(addr) <= instr_v;
            addr := addr + 1;
        end loop;
        wait;
    end process;

end behavioral;

tb/tb_instruction_memory.vhd
library ieee;
use ieee.std_logic_1164.all;
use ieee.numeric_std.all;
use std.textio.all;
use ieee.std_logic_textio.all;

entity tb_instruction_memory is
end tb_instruction_memory;

architecture behavioral of tb_instruction_memory is

  --------------------------------------------------------------------------
  -- Component
  --------------------------------------------------------------------------
  component Instruction_Memory
    port (
      clk        : in  std_logic;
      pc         : in  std_logic_vector(31 downto 0);
      instruction: out std_logic_vector(31 downto 0)
    );
  end component;

  --------------------------------------------------------------------------
  -- Signals
  --------------------------------------------------------------------------
  signal clk         : std_logic := '0';
  signal pc          : std_logic_vector(31 downto 0) := (others => '0');
  signal instruction : std_logic_vector(31 downto 0);
  constant clk_period : time := 10 ns;

begin

  --------------------------------------------------------------------------
  -- Clock
  --------------------------------------------------------------------------
  clk <= not clk after clk_period/2;

  --------------------------------------------------------------------------
  -- Instantiate DUT
  --------------------------------------------------------------------------
  uut: Instruction_Memory
    port map (
      clk =>clk,
      pc => pc,
      instruction => instruction
    );

  --------------------------------------------------------------------------
  -- Simulate PC
  --------------------------------------------------------------------------
  pc_proc: process
    variable pc_int : integer := 0;
  begin
    wait for 20 ns;  -- espera inicial

    for i in 0 to 15 loop  -- simula 16 instruções
      pc <= std_logic_vector(to_unsigned(pc_int, 32));
      wait for clk_period;
      report "PC=" & integer'image(pc_int/4) &
             " INSTR=" & to_hstring(instruction);
      pc_int := pc_int + 4;
    end loop;

    wait;
  end process;

end architecture behavioral;

sim/instruction.vcd
$date
  Sat Nov 15 22:00:49 2025
$end
$version
  GHDL v0
$end
$timescale
  1 fs
$end
$scope module standard $end
$upscope $end
$scope module textio $end
$upscope $end
$scope module std_logic_1164 $end
$upscope $end
$scope module numeric_std $end
$upscope $end
$scope module std_logic_textio $end
$upscope $end
$scope module tb_instruction_memory $end
$var reg 1 ! clk $end
$var reg 32 " pc[31:0] $end
$var reg 32 # instruction[31:0] $end
$scope module uut $end
$var reg 1 $ clk $end
$var reg 32 % pc[31:0] $end
$var reg 32 & instruction[31:0] $end
$comment mem is not handled $end
$upscope $end
$upscope $end
$enddefinitions $end
#0
0!
b00000000000000000000000000000000 "
b00000000000000000000000000000000 #
0$
b00000000000000000000000000000000 %
b00000000000000000000000000000000 &
#5000000
1!
1$
#10000000
0!
b00000000000000000000000000000001 #
0$
b00000000000000000000000000000001 &
#15000000
1!
1$
#20000000
0!
0$
#25000000
1!
1$
#30000000
0!
b00000000000000000000000000000100 "
b00000000000000000000000000000010 #
0$
b00000000000000000000000000000100 %
b00000000000000000000000000000010 &
#35000000
1!
1$
#40000000
0!
b00000000000000000000000000001000 "
b00010010001101000101011001111000 #
0$
b00000000000000000000000000001000 %
b00010010001101000101011001111000 &
#45000000
1!
1$
#50000000
0!
b00000000000000000000000000001100 "
b10101011110011011110111100000001 #
0$
b00000000000000000000000000001100 %
b10101011110011011110111100000001 &
#55000000
1!
1$
#60000000
0!
b00000000000000000000000000010000 "
b00001111000011110000111100001111 #
0$
b00000000000000000000000000010000 %
b00001111000011110000111100001111 &
#65000000
1!
1$
#70000000
0!
b00000000000000000000000000010100 "
b11110000111100001111000011110000 #
0$
b00000000000000000000000000010100 %
b11110000111100001111000011110000 &
#75000000
1!
1$
#80000000
0!
b00000000000000000000000000011000 "
b00000000000000000000000000000000 #
0$
b00000000000000000000000000011000 %
b00000000000000000000000000000000 &
#85000000
1!
1$
#90000000
0!
b00000000000000000000000000011100 "
0$
b00000000000000000000000000011100 %
#95000000
1!
1$
#100000000
0!
b00000000000000000000000000100000 "
0$
b00000000000000000000000000100000 %
#105000000
1!
1$
#110000000
0!
b00000000000000000000000000100100 "
0$
b00000000000000000000000000100100 %
#115000000
1!
1$
#120000000
0!
b00000000000000000000000000101000 "
0$
b00000000000000000000000000101000 %
#125000000
1!
1$
#130000000
0!
b00000000000000000000000000101100 "
0$
b00000000000000000000000000101100 %
#135000000
1!
1$
#140000000
0!
b00000000000000000000000000110000 "
0$
b00000000000000000000000000110000 %
#145000000
1!
1$
#150000000
0!
b00000000000000000000000000110100 "
0$
b00000000000000000000000000110100 %
#155000000
1!
1$
#160000000
0!
b00000000000000000000000000111000 "
0$
b00000000000000000000000000111000 %
#165000000
1!
1$
#170000000
0!
b00000000000000000000000000111100 "
0$
b00000000000000000000000000111100 %
