src/intAddSub.vhd
--------------------------------------------------------------------------------
--                        IntAddSub_w32_XcY_comb_uid2
-- VHDL generated for DummyFPGA @ 0MHz
-- This operator is part of the Infinite Virtual Library FloPoCoLib
-- All rights reserved 
-- Authors: Martin Kumm
--------------------------------------------------------------------------------
-- combinatorial
-- Clock period (ns): inf
-- Target frequency (MHz): 0
-- Input signals: X Y negY
-- Output signals: R
--  approx. input signal timings: X: 0.000000nsY: 0.000000nsnegY: 0.000000ns
--  approx. output signal timings: R: 0.000000ns

library ieee;
use ieee.std_logic_1164.all;
use ieee.numeric_std.all;
library std;
use std.textio.all;
library work;

entity IntAddSub_w32_XcY_comb_uid2 is
    port (X : in  std_logic_vector(31 downto 0);
          Y : in  std_logic_vector(31 downto 0);
          negY : in  std_logic;
          R : out  std_logic_vector(32 downto 0)   );
end entity;

architecture arch of IntAddSub_w32_XcY_comb_uid2 is
signal X_int :  std_logic_vector(32 downto 0);
   -- timing of X_int: 0.000000ns
signal Y_int :  std_logic_vector(32 downto 0);
   -- timing of Y_int: 0.000000ns
begin
   X_int <= std_logic_vector(resize(signed(X),33));
   Y_int <= std_logic_vector(-resize(signed(Y),33)) when negY='1' else std_logic_vector(resize(signed(Y),33));
   R <= std_logic_vector(resize(signed(X_int),33) + resize(signed(Y_int),33));
end architecture;

tb/tb_intAddSub.vhd
--------------------------------------------------------------------------------
--              tb_intAddSub
-- VHDL generated for DummyFPGA @ 0MHz
-- This operator is part of the Infinite Virtual Library FloPoCoLib
-- All rights reserved 
-- Authors: Florent de Dinechin, Cristian Klein, Nicolas Brunie (2007-2010)
--------------------------------------------------------------------------------
library ieee;
use ieee.std_logic_1164.all;
use ieee.numeric_std.all;
library std;
use std.textio.all;
library work;

entity tb_intAddSub is
end entity;

architecture behavorial of tb_intAddSub is
   component IntAddSub_w32_XcY_comb_uid2 is
      port ( X : in  std_logic_vector(31 downto 0);
             Y : in  std_logic_vector(31 downto 0);
             negY : in  std_logic;
             R : out  std_logic_vector(32 downto 0)   );
   end component;
signal X :  std_logic_vector(31 downto 0);
   -- timing of X: 0.000000ns
signal Y :  std_logic_vector(31 downto 0);
   -- timing of Y: 0.000000ns
signal negY :  std_logic;
   -- timing of negY: 0.000000ns
signal R :  std_logic_vector(32 downto 0);
   -- timing of R: 0.000000ns
signal clk :  std_logic;
   -- timing of clk: 0.000000ns
signal rst :  std_logic;
   -- timing of rst: 0.000000ns

 -- converts std_logic into a character
   function chr(sl: std_logic) return character is
      variable c: character;
   begin
      case sl is
         when 'U' => c:= 'U';
         when 'X' => c:= 'X';
         when '0' => c:= '0';
         when '1' => c:= '1';
         when 'Z' => c:= 'Z';
         when 'W' => c:= 'W';
         when 'L' => c:= 'L';
         when 'H' => c:= 'H';
         when '-' => c:= '-';
      end case;
      return c;
   end chr;

   -- converts bit to std_logic (1 to 1)
   function to_stdlogic(b : bit) return std_logic is
       variable sl : std_logic;
   begin
      case b is 
         when '0' => sl := '0';
         when '1' => sl := '1';
      end case;
      return sl;
   end to_stdlogic;

   -- converts std_logic into a string (1 to 1)
   function str(sl: std_logic) return string is
    variable s: string(1 to 1);
    begin
      s(1) := chr(sl);
      return s;
   end str;

   -- converts std_logic_vector into a string (binary base)
   -- (this also takes care of the fact that the range of
   --  a string is natural while a std_logic_vector may
   --  have an integer range)
   function str(slv: std_logic_vector) return string is
      variable result : string (1 to slv'length);
      variable r : integer;
   begin
      r := 1;
      for i in slv'range loop
         result(r) := chr(slv(i));
         r := r + 1;
      end loop;
      return result;
   end str;

   function testLine(testCounter:integer; expectedOutputS: string(1 to 10000); expectedOutputSize: integer; R:  std_logic_vector(32 downto 0)) return boolean is
      variable expectedOutput: line;
      variable possibilityNumber : integer;
      variable testSuccess: boolean;
      variable errorMessage: string(1 to 10000);
      variable testSuccess_R: boolean;
      variable expected_R: bit_vector (32 downto 0); -- for list of values
      variable inf_R: bit_vector (32 downto 0); -- for intervals
      variable sup_R: bit_vector (32 downto 0); -- for intervals
   begin
      write(expectedOutput, expectedOutputS);
      read(expectedOutput, possibilityNumber); -- for R
      if possibilityNumber = 0 then
         -- TODO define what it means to have 0 possible output. Currently it means a test fails...
      end if;
      if possibilityNumber > 0 then -- a list of values
      testSuccess_R := false;
         for i in 1 to possibilityNumber loop
            read(expectedOutput, expected_R);
            if R = to_stdlogicvector(expected_R) then
               testSuccess_R := true;
            end if;
            end loop;
      end if;
      if possibilityNumber < 0  then -- an interval
         read(expectedOutput, inf_R);
         read(expectedOutput, sup_R);
         if possibilityNumber =-1  then -- an unsigned interval
            testSuccess_R := (R >= to_stdlogicvector(inf_R)) and (R <= to_stdlogicvector(sup_R));
         elsif possibilityNumber =-2  then -- a signed interval
            testSuccess_R := (signed(R) >= signed(to_stdlogicvector(inf_R))) and (signed(R) <= signed(to_stdlogicvector(sup_R)));
         end if;
      end if;
      if testSuccess_R = false then
         report("Test #" & integer'image(testCounter) & ", incorrect output for R: " & lf & " expected values: " & expectedOutputS(1 to expectedOutputSize) & lf  & "          result:    " & str(R) ) severity error;
      end if;
      
      testSuccess := true and testSuccess_R;
      return testSuccess;
   end testLine;

begin
   -- Ticking clock signal
   process
   begin
      clk <= '0';
      wait for 5 ns;
      clk <= '1';
      wait for 5 ns;
   end process;

   test: IntAddSub_w32_XcY_comb_uid2
      port map ( X => X,
                 Y => Y,
                 negY => negY,
                 R => R);
   -- Process that sets the inputs  (read from a file) 
   process
      variable input, expectedOutput : line; 
      variable tmpChar : character;
      file inputsFile : text is "tests/intAddSub.input"; 
      variable V_X : bit_vector(31 downto 0);
      variable V_Y : bit_vector(31 downto 0);
      variable V_negY : bit_vector(0 downto 0);
      variable V_R : bit_vector(32 downto 0);
   begin
      -- Send reset
      rst <= '1';
      wait for 10 ns;
      rst <= '0';
      readline(inputsFile, input); -- skip the first line of advertising
      while not endfile(inputsFile) loop
         readline(inputsFile, input); -- skip the comment line
         readline(inputsFile, input);
         readline(inputsFile, expectedOutput); -- comment line, unused in this process
         readline(inputsFile, expectedOutput); -- unused in this process
         read(input ,V_X);
         read(input,tmpChar);
         X <= to_stdlogicvector(V_X);
         read(input ,V_Y);
         read(input,tmpChar);
         Y <= to_stdlogicvector(V_Y);
         read(input ,V_negY);
         read(input,tmpChar);
         negY <= to_stdlogicvector(V_negY)(0);
         wait for 10 ns;
      end loop;
         wait for 100 ns; -- wait for pipeline to flush (and some more)
   end process;

    -- Process that verifies the corresponding output
   process
      file inputsFile : text is "tests/intAddSub.input"; 
      variable input, expectedOutput : line; 
      variable testCounter : integer := 1;
      variable errorCounter : integer := 0;
      variable expectedOutputString : string(1 to 10000);
      variable testSuccess: boolean;
   begin
      wait for 12 ns; -- wait for reset 
      readline(inputsFile, input); -- skip the first line of advertising
      while not endfile(inputsFile) loop
         readline(inputsFile, input); -- input comment, unused
         readline(inputsFile, input); -- input line, unused
         readline(inputsFile, expectedOutput); -- comment line, unused in this process
         readline(inputsFile, expectedOutput);
         expectedOutputString := expectedOutput.all & (expectedOutput'Length+1 to 10000 => ' ');
         testSuccess := testLine(testCounter, expectedOutputString, expectedOutput'Length, R);
         if not testSuccess then 
               errorCounter := errorCounter + 1; -- incrementing global error counter
         end if;
            testCounter := testCounter + 1; -- incrementing global error counter
         wait for 10 ns;
      end loop;
      report integer'image(errorCounter) & " error(s) encoutered." severity note;
      report "End of simulation after " & integer'image(testCounter-1) & " tests" severity note;
   end process;

end architecture;

sim/intAddSub.vcd
$date
  Sat Nov  1 21:18:25 2025
$end
$version
  GHDL v0
$end
$timescale
  1 fs
$end
$scope module standard $end
$upscope $end
$scope module std_logic_1164 $end
$upscope $end
$scope module numeric_std $end
$upscope $end
$scope module textio $end
$upscope $end
$scope module tb_intaddsub $end
$var reg 32 ! x[31:0] $end
$var reg 32 " y[31:0] $end
$var reg 1 # negy $end
$var reg 33 $ r[32:0] $end
$var reg 1 % clk $end
$var reg 1 & rst $end
$scope module test $end
$var reg 32 ' x[31:0] $end
$var reg 32 ( y[31:0] $end
$var reg 1 ) negy $end
$var reg 33 * r[32:0] $end
$var reg 33 + x_int[32:0] $end
$var reg 33 , y_int[32:0] $end
$upscope $end
$upscope $end
$enddefinitions $end
#0
bUUUUUUUUUUUUUUUUUUUUUUUUUUUUUUUU !
bUUUUUUUUUUUUUUUUUUUUUUUUUUUUUUUU "
U#
bXXXXXXXXXXXXXXXXXXXXXXXXXXXXXXXXX $
0%
1&
bUUUUUUUUUUUUUUUUUUUUUUUUUUUUUUUU '
bUUUUUUUUUUUUUUUUUUUUUUUUUUUUUUUU (
U)
bXXXXXXXXXXXXXXXXXXXXXXXXXXXXXXXXX *
bUUUUUUUUUUUUUUUUUUUUUUUUUUUUUUUUU +
bUUUUUUUUUUUUUUUUUUUUUUUUUUUUUUUUU ,
#5000000
1%
#10000000
b10000000000000000000000000000000 !
b00000000000000000000000000000000 "
1#
b110000000000000000000000000000000 $
0%
0&
b10000000000000000000000000000000 '
b00000000000000000000000000000000 (
1)
b110000000000000000000000000000000 *
b110000000000000000000000000000000 +
b000000000000000000000000000000000 ,
#12000000
#15000000
1%
#20000000
b00000000000000000000000000000000 !
b10000000000000000000000000000000 "
b010000000000000000000000000000000 $
0%
b00000000000000000000000000000000 '
b10000000000000000000000000000000 (
b010000000000000000000000000000000 *
b000000000000000000000000000000000 +
b010000000000000000000000000000000 ,
#22000000
#25000000
1%
#30000000
b00000000000000000000000000000000 "
b000000000000000000000000000000000 $
0%
b00000000000000000000000000000000 (
b000000000000000000000000000000000 *
b000000000000000000000000000000000 ,
#32000000
#35000000
1%
#40000000
b10011101010011100101010100110010 !
b10111101101011100110001100100011 "
b111011111100111111111001000001111 $
0%
b10011101010011100101010100110010 '
b10111101101011100110001100100011 (
b111011111100111111111001000001111 *
b110011101010011100101010100110010 +
b001000010010100011001110011011101 ,
#42000000
#45000000
1%
#50000000
b01000101110001001111011110000001 !
b01101111001100010101001100110111 "
0#
b010110100111101100100101010111000 $
0%
b01000101110001001111011110000001 '
b01101111001100010101001100110111 (
0)
b010110100111101100100101010111000 *
b001000101110001001111011110000001 +
b001101111001100010101001100110111 ,
#52000000
#55000000
1%
#60000000
b10010011111111100101011000000001 !
b10010111010001001001111110101110 "
1#
b111111100101110011011011001010011 $
0%
b10010011111111100101011000000001 '
b10010111010001001001111110101110 (
1)
b111111100101110011011011001010011 *
b110010011111111100101011000000001 +
b001101000101110110110000001010010 ,
#62000000
#65000000
1%
#70000000
b00001001001111110010010001010010 !
b11101001100010100111110011000010 "
0#
b111110010110010011010000100010100 $
0%
b00001001001111110010010001010010 '
b11101001100010100111110011000010 (
0)
b111110010110010011010000100010100 *
b000001001001111110010010001010010 +
b111101001100010100111110011000010 ,
#72000000
#75000000
1%
#80000000
b01000001010100110011111100110110 !
b11101111010000101010000100111011 "
b000110000100101011110000001110001 $
0%
b01000001010100110011111100110110 '
b11101111010000101010000100111011 (
b000110000100101011110000001110001 *
b001000001010100110011111100110110 +
b111101111010000101010000100111011 ,
#82000000
#85000000
1%
#90000000
b10100001111110011010101011110100 !
b10110111100001110110110000111001 "
1#
b111101010011100100011111010111011 $
0%
b10100001111110011010101011110100 '
b10110111100001110110110000111001 (
1)
b111101010011100100011111010111011 *
b110100001111110011010101011110100 +
b001001000011110001001001111000111 ,
#92000000
#95000000
1%
#100000000
b00101011110111000100101101100000 !
b01111100110110001111011100110010 "
0#
b010101000101101010100001010010010 $
0%
b00101011110111000100101101100000 '
b01111100110110001111011100110010 (
0)
b010101000101101010100001010010010 *
b000101011110111000100101101100000 +
b001111100110110001111011100110010 ,
#102000000
#105000000
1%
#110000000
b10010000111110101110000001010000 !
b10010111011011010110100001010000 "
b100101000011010000100100010100000 $
0%
b10010000111110101110000001010000 '
b10010111011011010110100001010000 (
b100101000011010000100100010100000 *
b110010000111110101110000001010000 +
b110010111011011010110100001010000 ,
#112000000
#115000000
1%
#120000000
b01011001001101011011000011110110 !
b00010010000011011100101001101101 "
b001101011010000110111101101100011 $
0%
b01011001001101011011000011110110 '
b00010010000011011100101001101101 (
b001101011010000110111101101100011 *
b001011001001101011011000011110110 +
b000010010000011011100101001101101 ,
#122000000
#125000000
1%
#130000000
b01011010000000111100000010110010 !
b01001011001111110100101110010100 "
b010100101010000110000110001000110 $
0%
b01011010000000111100000010110010 '
b01001011001111110100101110010100 (
b010100101010000110000110001000110 *
b001011010000000111100000010110010 +
b001001011001111110100101110010100 ,
#132000000
#135000000
1%
#140000000
b01010111111001100101001010110001 !
b10011000100000011110010000111110 "
1#
b010111111011001000110111001110011 $
0%
b01010111111001100101001010110001 '
b10011000100000011110010000111110 (
1)
b010111111011001000110111001110011 *
b001010111111001100101001010110001 +
b001100111011111100001101111000010 ,
#142000000
#145000000
1%
#150000000
b10000010101000000100000010010110 !
b00110111000101001101101100111000 "
b101001011100010110110010101011110 $
0%
b10000010101000000100000010010110 '
b00110111000101001101101100111000 (
b101001011100010110110010101011110 *
b110000010101000000100000010010110 +
b111001000111010110010010011001000 ,
#152000000
#155000000
1%
#160000000
b01101101111110100001111001100000 !
b00111101011001001000000011010011 "
0#
b010101011010111101001111100110011 $
0%
b01101101111110100001111001100000 '
b00111101011001001000000011010011 (
0)
b010101011010111101001111100110011 *
b001101101111110100001111001100000 +
b000111101011001001000000011010011 ,
#162000000
#165000000
1%
#170000000
b10001111101101001010111011100000 !
b10111100101001111101111010011000 "
1#
b111010011000011001101000001001000 $
0%
b10001111101101001010111011100000 '
b10111100101001111101111010011000 (
1)
b111010011000011001101000001001000 *
b110001111101101001010111011100000 +
b001000011010110000010000101101000 ,
#172000000
#175000000
1%
#180000000
b00110010010000101000011111100101 !
b01101000001011110000111011010101 "
b111001010000100110111100100010000 $
0%
b00110010010000101000011111100101 '
b01101000001011110000111011010101 (
b111001010000100110111100100010000 *
b000110010010000101000011111100101 +
b110010111110100001111000100101011 ,
#182000000
#185000000
1%
#190000000
b11100110001101011111101101100111 !
b00001110000110100000101101110000 "
0#
b111110100010100000000011011010111 $
0%
b11100110001101011111101101100111 '
b00001110000110100000101101110000 (
0)
b111110100010100000000011011010111 *
b111100110001101011111101101100111 +
b000001110000110100000101101110000 ,
#192000000
#195000000
1%
#200000000
b00011111111011001110101100010000 !
b10011101010000011000111111011010 "
1#
b010000010101010110101101100110110 $
0%
b00011111111011001110101100010000 '
b10011101010000011000111111011010 (
1)
b010000010101010110101101100110110 *
b000011111111011001110101100010000 +
b001100010101111100111000000100110 ,
#202000000
#205000000
1%
#210000000
b01110111000111101001011001100011 !
b11101000100001011011000111011001 "
b010001110100110001110010010001010 $
0%
b01110111000111101001011001100011 '
b11101000100001011011000111011001 (
b010001110100110001110010010001010 *
b001110111000111101001011001100011 +
b000010111011110100100111000100111 ,
#212000000
#215000000
1%
#220000000
b10010111001101000101100000111100 !
b11001111000101010101001000111011 "
b111001000000111110000011000000001 $
0%
b10010111001101000101100000111100 '
b11001111000101010101001000111011 (
b111001000000111110000011000000001 *
b110010111001101000101100000111100 +
b000110000111010101010110111000101 ,
#222000000
#225000000
1%
#230000000
b10001110010101110000001100000110 !
b11110001101111001111010011110101 "
b110011100100110100000111000010001 $
0%
b10001110010101110000001100000110 '
b11110001101111001111010011110101 (
b110011100100110100000111000010001 *
b110001110010101110000001100000110 +
b000001110010000110000101100001011 ,
#232000000
#235000000
1%
#240000000
b10101010011110111100001101001011 !
b10001000101110010111101011110011 "
0#
b100110011001101010011111000111110 $
0%
b10101010011110111100001101001011 '
b10001000101110010111101011110011 (
0)
b100110011001101010011111000111110 *
b110101010011110111100001101001011 +
b110001000101110010111101011110011 ,
#242000000
#245000000
1%
#250000000
b01001111010000101101000110111010 !
b01110000111110011100111111101001 "
1#
b111011110010010010000000111010001 $
0%
b01001111010000101101000110111010 '
b01110000111110011100111111101001 (
1)
b111011110010010010000000111010001 *
b001001111010000101101000110111010 +
b110001111000001100011000000010111 ,
#252000000
#255000000
1%
#260000000
b10000011000001000100001001001110 !
b10000100100100011111111110001011 "
b111111110011100100100001011000011 $
0%
b10000011000001000100001001001110 '
b10000100100100011111111110001011 (
b111111110011100100100001011000011 *
b110000011000001000100001001001110 +
b001111011011011100000000001110101 ,
#262000000
#265000000
1%
#270000000
b00110100101010001001101001111001 !
b10111010111111110011110101011101 "
b001111001101010010101110100011100 $
0%
b00110100101010001001101001111001 '
b10111010111111110011110101011101 (
b001111001101010010101110100011100 *
b000110100101010001001101001111001 +
b001000101000000001100001010100011 ,
#272000000
#275000000
1%
#280000000
b00001010110000010111000010110001 !
b11100110100100001111101110001101 "
b000100100001100000111010100100100 $
0%
b00001010110000010111000010110001 '
b11100110100100001111101110001101 (
b000100100001100000111010100100100 *
b000001010110000010111000010110001 +
b000011001011011110000010001110011 ,
#282000000
#285000000
1%
#290000000
b01111110110010111101101000010011 !
b01010001101011100101101110110010 "
b000101101000111010111111001100001 $
0%
b01111110110010111101101000010011 '
b01010001101011100101101110110010 (
b000101101000111010111111001100001 *
b001111110110010111101101000010011 +
b110101110010100011010010001001110 ,
#292000000
#295000000
1%
#300000000
b01010010010110011101111100111110 !
b00011000100010001011100000101011 "
0#
b001101010111000101001011101101001 $
0%
b01010010010110011101111100111110 '
b00011000100010001011100000101011 (
0)
b001101010111000101001011101101001 *
b001010010010110011101111100111110 +
b000011000100010001011100000101011 ,
#302000000
#305000000
1%
#310000000
b00100110011010100101001001101101 !
b10111010011111011000101000110011 "
b111100000111001111101110010100000 $
0%
b00100110011010100101001001101101 '
b10111010011111011000101000110011 (
b111100000111001111101110010100000 *
b000100110011010100101001001101101 +
b110111010011111011000101000110011 ,
#312000000
#315000000
1%
#320000000
b11001110001101111010100100010001 !
b01010111101111011101100010010001 "
b000100101111101011000000110100010 $
0%
b11001110001101111010100100010001 '
b01010111101111011101100010010001 (
b000100101111101011000000110100010 *
b111001110001101111010100100010001 +
b001010111101111011101100010010001 ,
#322000000
#325000000
1%
#330000000
b00101011101010000000101001011101 !
b01011000111110110010101010100110 "
1#
b111010010101011001101111110110111 $
0%
b00101011101010000000101001011101 '
b01011000111110110010101010100110 (
1)
b111010010101011001101111110110111 *
b000101011101010000000101001011101 +
b110100111000001001101010101011010 ,
#332000000
#335000000
1%
#340000000
b01001100100000100000100100010000 !
b01100100011010000111010111111011 "
b111101000000110011001001100010101 $
0%
b01001100100000100000100100010000 '
b01100100011010000111010111111011 (
b111101000000110011001001100010101 *
b001001100100000100000100100010000 +
b110011011100101111000101000000101 ,
#342000000
#345000000
1%
#350000000
b10001000111100000010010110011101 !
b01101100100001001000001010000101 "
b100011100011010111010001100011000 $
0%
b10001000111100000010010110011101 '
b01101100100001001000001010000101 (
b100011100011010111010001100011000 *
b110001000111100000010010110011101 +
b110010011011110110111110101111011 ,
#352000000
#355000000
1%
#360000000
b00100111000010111001110000010001 !
b01000100010101001000010011010011 "
0#
b001101011011000000010000011100100 $
0%
b00100111000010111001110000010001 '
b01000100010101001000010011010011 (
0)
b001101011011000000010000011100100 *
b000100111000010111001110000010001 +
b001000100010101001000010011010011 ,
#362000000
#365000000
1%
#370000000
b10100110110010101110000001001011 !
b00011001110101100000111110111001 "
b111000000101000001111000000000100 $
0%
b10100110110010101110000001001011 '
b00011001110101100000111110111001 (
b111000000101000001111000000000100 *
b110100110110010101110000001001011 +
b000011001110101100000111110111001 ,
#372000000
#375000000
1%
#380000000
b00111110010100101001010001101000 !
b11101101010100000011110101101101 "
1#
b001010001000000100101011011111011 $
0%
b00111110010100101001010001101000 '
b11101101010100000011110101101101 (
1)
b001010001000000100101011011111011 *
b000111110010100101001010001101000 +
b000010010101011111100001010010011 ,
#382000000
#385000000
1%
#390000000
b10010101000011101110001110110100 !
b10111000000101010110001011110000 "
b111011100111110011000000011000100 $
0%
b10010101000011101110001110110100 '
b10111000000101010110001011110000 (
b111011100111110011000000011000100 *
b110010101000011101110001110110100 +
b001000111111010101001110100010000 ,
#392000000
#395000000
1%
#400000000
b11100010001111100011000101111001 !
b00001101111011111101101100101101 "
b111010100010011100101011001001100 $
0%
b11100010001111100011000101111001 '
b00001101111011111101101100101101 (
b111010100010011100101011001001100 *
b111100010001111100011000101111001 +
b111110010000100000010010011010011 ,
#402000000
#405000000
1%
#410000000
b11011100110111101111110001011101 !
b11111101110001010111100001111010 "
0#
b111011010101001000111010011010111 $
0%
b11011100110111101111110001011101 '
b11111101110001010111100001111010 (
0)
b111011010101001000111010011010111 *
b111011100110111101111110001011101 +
b111111101110001010111100001111010 ,
#412000000
#415000000
1%
#420000000
b11111000100100100010000111111011 !
b01010110011110110001111001110010 "
1#
b110100010000101110000001110001001 $
0%
b11111000100100100010000111111011 '
b01010110011110110001111001110010 (
1)
b110100010000101110000001110001001 *
b111111000100100100010000111111011 +
b110101001100001001110000110001110 ,
#422000000
#425000000
1%
#430000000
b00010010011100011000000101111001 !
b10111111110011100010010001011010 "
b001010010101000110101110100011111 $
0%
b00010010011100011000000101111001 '
b10111111110011100010010001011010 (
b001010010101000110101110100011111 *
b000010010011100011000000101111001 +
b001000000001100011101101110100110 ,
#432000000
#435000000
1%
#440000000
b10110011001100000111110000000001 !
b00110110000111011101000111110010 "
0#
b111101001010011100100110111110011 $
0%
b10110011001100000111110000000001 '
b00110110000111011101000111110010 (
0)
b111101001010011100100110111110011 *
b110110011001100000111110000000001 +
b000110110000111011101000111110010 ,
#442000000
#445000000
1%
#450000000
b00000000010101101111100000010100 !
b10001000010001011111000101111111 "
1#
b001111000000100010000011010010101 $
0%
b00000000010101101111100000010100 '
b10001000010001011111000101111111 (
1)
b001111000000100010000011010010101 *
b000000000010101101111100000010100 +
b001110111101110100000111010000001 ,
#452000000
#455000000
1%
#460000000
b11101100110000110101011010000101 !
b00001011110111001000000111111001 "
0#
b111111000100111111101100001111110 $
0%
b11101100110000110101011010000101 '
b00001011110111001000000111111001 (
0)
b111111000100111111101100001111110 *
b111101100110000110101011010000101 +
b000001011110111001000000111111001 ,
#462000000
#465000000
1%
#470000000
b01101000011101110001010111000001 !
b01111000100111000111010011110111 "
1#
b111101111110110101010000011001010 $
0%
b01101000011101110001010111000001 '
b01111000100111000111010011110111 (
1)
b111101111110110101010000011001010 *
b001101000011101110001010111000001 +
b110000111011000111000101100001001 ,
#472000000
#475000000
1%
#480000000
b00101011010001100101001101000100 !
b10000011111101100011110010011111 "
b010100111010100000001011010100101 $
0%
b00101011010001100101001101000100 '
b10000011111101100011110010011111 (
b010100111010100000001011010100101 *
b000101011010001100101001101000100 +
b001111100000010011100001101100001 ,
#482000000
#485000000
1%
#490000000
b00110010011111001101101111111000 !
b00000101001001010111011111101001 "
0#
b000110111101000100101001111100001 $
0%
b00110010011111001101101111111000 '
b00000101001001010111011111101001 (
0)
b000110111101000100101001111100001 *
b000110010011111001101101111111000 +
b000000101001001010111011111101001 ,
#492000000
#495000000
1%
#500000000
b10000111010100110001001000011111 !
b11101010111000000010110010001101 "
1#
b110011100011100101110010110010010 $
0%
b10000111010100110001001000011111 '
b11101010111000000010110010001101 (
1)
b110011100011100101110010110010010 *
b110000111010100110001001000011111 +
b000010101000111111101001101110011 ,
#502000000
#505000000
1%
#510000000
b10111000101001110010101110010001 !
b11010111111100110101011111101000 "
0#
b110010000100110101000001101111001 $
0%
b10111000101001110010101110010001 '
b11010111111100110101011111101000 (
0)
b110010000100110101000001101111001 *
b110111000101001110010101110010001 +
b111010111111100110101011111101000 ,
#512000000
#515000000
1%
#520000000
b11101001001100100010000000010001 !
b10111101000110110011011101101000 "
b110100110010011010101011101111001 $
0%
b11101001001100100010000000010001 '
b10111101000110110011011101101000 (
b110100110010011010101011101111001 *
b111101001001100100010000000010001 +
b110111101000110110011011101101000 ,
#522000000
#525000000
1%
#530000000
b10110110110001010101010110001011 !
b11001011101110011010010010010111 "
b110000010011111101111101000100010 $
0%
b10110110110001010101010110001011 '
b11001011101110011010010010010111 (
b110000010011111101111101000100010 *
b110110110110001010101010110001011 +
b111001011101110011010010010010111 ,
#532000000
#535000000
1%
#540000000
b10010101101101001001000001101100 !
b11010100010101111101101001111100 "
1#
b111000001010111001011010111110000 $
0%
b10010101101101001001000001101100 '
b11010100010101111101101001111100 (
1)
b111000001010111001011010111110000 *
b110010101101101001001000001101100 +
b000101011101010000010010110000100 ,
#542000000
#545000000
1%
#550000000
b00100010010111000001011111001110 !
b10000010100101000100001010000000 "
b010011111110001111101010101001110 $
0%
b00100010010111000001011111001110 '
b10000010100101000100001010000000 (
b010011111110001111101010101001110 *
b000100010010111000001011111001110 +
b001111101011010111011110110000000 ,
#552000000
#555000000
1%
#560000000
b11011010010001011011101001110111 !
b00100110000110010110000001100001 "
0#
b000000000010111110001101011011000 $
0%
b11011010010001011011101001110111 '
b00100110000110010110000001100001 (
0)
b000000000010111110001101011011000 *
b111011010010001011011101001110111 +
b000100110000110010110000001100001 ,
#562000000
#565000000
1%
#570000000
b10101111001110010000111101101100 !
b10111010011010101001100100000011 "
b101101001101000111010100001101111 $
0%
b10101111001110010000111101101100 '
b10111010011010101001100100000011 (
b101101001101000111010100001101111 *
b110101111001110010000111101101100 +
b110111010011010101001100100000011 ,
#572000000
#575000000
1%
#580000000
b01100011001001011110000011110001 !
b11000110111010111001101110001001 "
1#
b010011100001110100100010101101000 $
0%
b01100011001001011110000011110001 '
b11000110111010111001101110001001 (
1)
b010011100001110100100010101101000 *
b001100011001001011110000011110001 +
b000111001000101000110010001110111 ,
#582000000
#585000000
1%
#590000000
b01100101110000101000010001001100 !
b00100110000011011101011111110001 "
0#
b010001011110100000101110000111101 $
0%
b01100101110000101000010001001100 '
b00100110000011011101011111110001 (
0)
b010001011110100000101110000111101 *
b001100101110000101000010001001100 +
b000100110000011011101011111110001 ,
#592000000
#595000000
1%
#600000000
b00111010111011011101000110111101 !
b10110000101010011001111011100100 "
1#
b010001010010001000011001011011001 $
0%
b00111010111011011101000110111101 '
b10110000101010011001111011100100 (
1)
b010001010010001000011001011011001 *
b000111010111011011101000110111101 +
b001001111010101100110000100011100 ,
#602000000
#605000000
1%
#610000000
b00100011010010000011111011010001 !
b00100001101000010111101110011011 "
0#
b001000100111010011011101001101100 $
0%
b00100011010010000011111011010001 '
b00100001101000010111101110011011 (
0)
b001000100111010011011101001101100 *
b000100011010010000011111011010001 +
b000100001101000010111101110011011 ,
#612000000
#615000000
1%
#620000000
b01111010011100110000011101011011 !
b10010101010011000111111011001111 "
1#
b011100101001001101000100010001100 $
0%
b01111010011100110000011101011011 '
b10010101010011000111111011001111 (
1)
b011100101001001101000100010001100 *
b001111010011100110000011101011011 +
b001101010101100111000000100110001 ,
#622000000
#625000000
1%
#630000000
b10110100001111110101011101110111 !
b11010011101011110000101111011001 "
b111100000100100000100101110011110 $
0%
b10110100001111110101011101110111 '
b11010011101011110000101111011001 (
b111100000100100000100101110011110 *
b110110100001111110101011101110111 +
b000101100010100001111010000100111 ,
#632000000
#635000000
1%
#640000000
b11001100100001111111110010111001 !
b11100111101000110101000100110000 "
b111100100111001001010101110001001 $
0%
b11001100100001111111110010111001 '
b11100111101000110101000100110000 (
b111100100111001001010101110001001 *
b111001100100001111111110010111001 +
b000011000010111001010111011010000 ,
#642000000
#645000000
1%
#650000000
b01111111100111011011000111010010 !
b01111000111100000100101111000100 "
b000000110101011010110011000001110 $
0%
b01111111100111011011000111010010 '
b01111000111100000100101111000100 (
b000000110101011010110011000001110 *
b001111111100111011011000111010010 +
b110000111000011111011010000111100 ,
#652000000
#655000000
1%
#660000000
b01001100110010000011111000101001 !
b11001011101011101111011000000101 "
0#
b000011000011101110011010000101110 $
0%
b01001100110010000011111000101001 '
b11001011101011101111011000000101 (
0)
b000011000011101110011010000101110 *
b001001100110010000011111000101001 +
b111001011101011101111011000000101 ,
#662000000
#665000000
1%
#670000000
b10010010011101000001000101010001 !
b10000101011100111011010100111000 "
1#
b000001101000000000101110000011001 $
0%
b10010010011101000001000101010001 '
b10000101011100111011010100111000 (
1)
b000001101000000000101110000011001 *
b110010010011101000001000101010001 +
b001111010100011000100101011001000 ,
#672000000
#675000000
1%
#680000000
b10001111100001111100010011111011 !
b11010101010111001110111100110001 "
b110111010001010101101010111001010 $
0%
b10001111100001111100010011111011 '
b11010101010111001110111100110001 (
b110111010001010101101010111001010 *
b110001111100001111100010011111011 +
b000101010101000110001000011001111 ,
#682000000
#685000000
1%
#690000000
b01001000001001110111000010110100 !
b11101100101111011010001011000101 "
0#
b000110100111001010001001101111001 $
0%
b01001000001001110111000010110100 '
b11101100101111011010001011000101 (
0)
b000110100111001010001001101111001 *
b001001000001001110111000010110100 +
b111101100101111011010001011000101 ,
#692000000
#695000000
1%
#700000000
b10100101011001111000001111010001 !
b00110111111101001010100111000100 "
b111011101010111000010110110010101 $
0%
b10100101011001111000001111010001 '
b00110111111101001010100111000100 (
b111011101010111000010110110010101 *
b110100101011001111000001111010001 +
b000110111111101001010100111000100 ,
#702000000
#705000000
1%
#710000000
b00000000010101010011010001100001 !
b00101011110110011000011111010110 "
1#
b111010100011110111010110010001011 $
0%
b00000000010101010011010001100001 '
b00101011110110011000011111010110 (
1)
b111010100011110111010110010001011 *
b000000000010101010011010001100001 +
b111010100001001100111100000101010 ,
#712000000
#715000000
1%
#720000000
b00001001110111111001011101111000 !
b10001000011010111110110101001011 "
b010000001011100111010101000101101 $
0%
b00001001110111111001011101111000 '
b10001000011010111110110101001011 (
b010000001011100111010101000101101 *
b000001001110111111001011101111000 +
b001110111100101000001001010110101 ,
#722000000
#725000000
1%
#730000000
b10001100000000110110111101111110 !
b10100111001000010010110111000111 "
0#
b100110011001001001001110101000101 $
0%
b10001100000000110110111101111110 '
b10100111001000010010110111000111 (
0)
b100110011001001001001110101000101 *
b110001100000000110110111101111110 +
b110100111001000010010110111000111 ,
#732000000
#735000000
1%
