src/memory.vhd
-- codigo base localizado no link abaixo. Alterado de 16 para 32 bits
-- fpga4student.com: FPGA projects, Verilog projects, VHDL projects
-- VHDL project: VHDL code for single-cycle MIPS Processor
-- VHDL code for the data Memory of the MIPS Processor 16 bits
library IEEE;
use IEEE.STD_LOGIC_1164.ALL;
USE IEEE.numeric_std.all;  
entity Data_Memory_VHDL is
port (
 clk: in std_logic;
 mem_access_addr: in std_logic_Vector(31 downto 0);
 mem_write_data: in std_logic_Vector(31 downto 0);
 mem_write_en,mem_read:in std_logic;
 mem_read_data: out std_logic_Vector(31 downto 0)
);
end Data_Memory_VHDL;

architecture Behavioral of Data_Memory_VHDL is
signal i: integer;
signal ram_addr: std_logic_vector(9 downto 0);
type data_mem is array (0 to 1023 ) of std_logic_vector (31 downto 0);
signal RAM: data_mem := (others => (others => '0'));
begin

 ram_addr <= mem_access_addr(11 downto 2);
 process(clk)
 begin
    if(rising_edge(clk)) then
      if (mem_write_en='1') then
        ram(to_integer(unsigned(ram_addr))) <= mem_write_data;
      end if;
    end if;
 end process;
  mem_read_data <= ram(to_integer(unsigned(ram_addr))) when (mem_read='1') else x"00000000";

end Behavioral;

tb/tb_memory.vhd
library ieee;
use ieee.std_logic_1164.all;
use ieee.numeric_std.all;
use std.textio.all;
use ieee.std_logic_textio.all;   -- <-- IMPORTANTE para hread

entity tb_memory is
end tb_memory;

architecture behavioral of tb_memory is

    component Data_Memory_VHDL 
    port (
        clk: in std_logic;
        mem_access_addr: in std_logic_vector(31 downto 0);
        mem_write_data: in std_logic_vector(31 downto 0);
        mem_write_en,mem_read: in std_logic;
        mem_read_data: out std_logic_vector(31 downto 0)
    );
    end component;

    signal clk              : std_logic := '0';
    signal mem_access_addr : std_logic_vector(31 downto 0);
    signal mem_write_data  : std_logic_vector(31 downto 0);
    signal mem_write_en    : std_logic;
    signal mem_read        : std_logic;
    signal mem_read_data   : std_logic_vector(31 downto 0);

begin

    clk <= not clk after 5 ns;

    uut: Data_Memory_VHDL 
        port map(
            clk => clk,
            mem_access_addr => mem_access_addr,
            mem_write_data => mem_write_data,
            mem_write_en => mem_write_en,
            mem_read => mem_read,
            mem_read_data => mem_read_data
        );

    ------------------------------------------------------
    -- PROCESSO DE LEITURA DO ARQUIVO HEX
    ------------------------------------------------------
    P1: process
        file f         : text open read_mode is "tests/memory.input";
        variable line_v: line;
        variable addr_v: std_logic_vector(31 downto 0);
        variable data_v: std_logic_vector(31 downto 0);
    begin
        --------------------------------------------------
        -- FASE DE LEITURA INICIAL
        --------------------------------------------------
        report "MEMORIA INICIAL";
        mem_read <= '1';
        for i in 0 to 5 loop
            mem_access_addr <= std_logic_vector(to_unsigned(i*4, 32));
            wait for 10 ns;
            report "ADDR=" & to_hstring(mem_access_addr) &
                    " DATA=" & to_hstring(mem_read_data);

        end loop;


        mem_write_en <= '0';
        mem_read <= '0';
        wait for 20 ns;
        report "ESCRITA NA MEMORIA";
        
        while not endfile(f) loop
            readline(f, line_v);

            -- LÊ ENDEREÇO EM HEX
            hread(line_v, addr_v);

            -- LÊ DADO EM HEX
            hread(line_v, data_v);
            
            mem_access_addr <= addr_v;
            mem_write_data <= data_v;

            mem_write_en <= '1';
            wait for 10 ns;
            mem_write_en <= '0';
            wait for 10 ns;
        end loop;

        --------------------------------------------------
        -- FASE DE LEITURA
        --------------------------------------------------
        mem_read <= '1';
        report "MEMORIA FINAL";
        
        for i in 0 to 5 loop
            mem_access_addr <= std_logic_vector(to_unsigned(i*4, 32));
            wait for 10 ns;
            report "ADDR=" & to_hstring(mem_access_addr) &
                    " DATA=" & to_hstring(mem_read_data);

        end loop;

        wait;
    end process;

end behavioral;

sim/memory.vcd
$date
  Sun Nov 16 12:44:06 2025
$end
$version
  GHDL v0
$end
$timescale
  1 fs
$end
$scope module standard $end
$upscope $end
$scope module textio $end
$upscope $end
$scope module std_logic_1164 $end
$upscope $end
$scope module numeric_std $end
$upscope $end
$scope module std_logic_textio $end
$upscope $end
$scope module tb_memory $end
$var reg 1 ! clk $end
$var reg 32 " mem_access_addr[31:0] $end
$var reg 32 # mem_write_data[31:0] $end
$var reg 1 $ mem_write_en $end
$var reg 1 % mem_read $end
$var reg 32 & mem_read_data[31:0] $end
$scope module uut $end
$var reg 1 ' clk $end
$var reg 32 ( mem_access_addr[31:0] $end
$var reg 32 ) mem_write_data[31:0] $end
$var reg 1 * mem_write_en $end
$var reg 1 + mem_read $end
$var reg 32 , mem_read_data[31:0] $end
$var integer 32 - i $end
$var reg 10 . ram_addr[9:0] $end
$comment ram is not handled $end
$upscope $end
$upscope $end
$enddefinitions $end
#0
0!
b00000000000000000000000000000000 "
bUUUUUUUUUUUUUUUUUUUUUUUUUUUUUUUU #
U$
1%
b00000000000000000000000000000000 &
0'
b00000000000000000000000000000000 (
bUUUUUUUUUUUUUUUUUUUUUUUUUUUUUUUU )
U*
1+
b00000000000000000000000000000000 ,
b10000000000000000000000000000000 -
b0000000000 .
#5000000
1!
1'
#10000000
0!
b00000000000000000000000000000100 "
0'
b00000000000000000000000000000100 (
b0000000001 .
#15000000
1!
1'
#20000000
0!
b00000000000000000000000000001000 "
0'
b00000000000000000000000000001000 (
b0000000010 .
#25000000
1!
1'
#30000000
0!
b00000000000000000000000000001100 "
0'
b00000000000000000000000000001100 (
b0000000011 .
#35000000
1!
1'
#40000000
0!
b00000000000000000000000000010000 "
0'
b00000000000000000000000000010000 (
b0000000100 .
#45000000
1!
1'
#50000000
0!
b00000000000000000000000000010100 "
0'
b00000000000000000000000000010100 (
b0000000101 .
#55000000
1!
1'
#60000000
0!
0$
0%
0'
0*
0+
#65000000
1!
1'
#70000000
0!
0'
#75000000
1!
1'
#80000000
0!
b00000000000000000000000000000000 "
b11011110101011011011111011101111 #
1$
0'
b00000000000000000000000000000000 (
b11011110101011011011111011101111 )
1*
b0000000000 .
#85000000
1!
1'
#90000000
0!
0$
0'
0*
#95000000
1!
1'
#100000000
0!
b00000000000000000000000000000100 "
b00010010001101000101011001111000 #
1$
0'
b00000000000000000000000000000100 (
b00010010001101000101011001111000 )
1*
b0000000001 .
#105000000
1!
1'
#110000000
0!
0$
0'
0*
#115000000
1!
1'
#120000000
0!
b00000000000000000000000000001000 "
b10101010101110111100110011011101 #
1$
0'
b00000000000000000000000000001000 (
b10101010101110111100110011011101 )
1*
b0000000010 .
#125000000
1!
1'
#130000000
0!
0$
0'
0*
#135000000
1!
1'
#140000000
0!
b00000000000000000000000000010100 "
b11111111111111111111111111111111 #
1$
0'
b00000000000000000000000000010100 (
b11111111111111111111111111111111 )
1*
b0000000101 .
#145000000
1!
1'
#150000000
0!
0$
0'
0*
#155000000
1!
1'
#160000000
0!
b00000000000000000000000000000000 "
1%
b11011110101011011011111011101111 &
0'
b00000000000000000000000000000000 (
1+
b11011110101011011011111011101111 ,
b0000000000 .
#165000000
1!
1'
#170000000
0!
b00000000000000000000000000000100 "
b00010010001101000101011001111000 &
0'
b00000000000000000000000000000100 (
b00010010001101000101011001111000 ,
b0000000001 .
#175000000
1!
1'
#180000000
0!
b00000000000000000000000000001000 "
b10101010101110111100110011011101 &
0'
b00000000000000000000000000001000 (
b10101010101110111100110011011101 ,
b0000000010 .
#185000000
1!
1'
#190000000
0!
b00000000000000000000000000001100 "
b00000000000000000000000000000000 &
0'
b00000000000000000000000000001100 (
b00000000000000000000000000000000 ,
b0000000011 .
#195000000
1!
1'
#200000000
0!
b00000000000000000000000000010000 "
0'
b00000000000000000000000000010000 (
b0000000100 .
#205000000
1!
1'
#210000000
0!
b00000000000000000000000000010100 "
b11111111111111111111111111111111 &
0'
b00000000000000000000000000010100 (
b11111111111111111111111111111111 ,
b0000000101 .
