src/register.vhd
library IEEE;
use IEEE.STD_LOGIC_1164.ALL;
use IEEE.numeric_std.all;  

entity register_file_VHDL is
port (
 clk, rst          : in std_logic;
 reg_write_en      : in std_logic;
 reg_write_dest    : in std_logic_vector(4 downto 0);
 reg_write_data    : in std_logic_vector(31 downto 0);
 reg_read_addr_1   : in std_logic_vector(4 downto 0);
 reg_read_data_1   : out std_logic_vector(31 downto 0);
 reg_read_addr_2   : in std_logic_vector(4 downto 0);
 reg_read_data_2   : out std_logic_vector(31 downto 0)
);
end register_file_VHDL;

architecture Behavioral of register_file_VHDL is

  type reg_type is array (0 to 7) of std_logic_vector(31 downto 0);
  signal reg_array : reg_type;

begin

  process(clk, rst) 
  begin
    if rst = '1' then
      reg_array(0) <= x"00000000";
      reg_array(1) <= x"00000000";
      reg_array(2) <= x"00000000";
      reg_array(3) <= x"00000000";
      reg_array(4) <= x"00000000";
      reg_array(5) <= x"00000000";
      reg_array(6) <= x"00000000";
      reg_array(7) <= x"00000000";

    elsif rising_edge(clk) then
      if reg_write_en = '1' then
        reg_array(to_integer(unsigned(reg_write_dest))) <= reg_write_data;
      end if;
    end if;
  end process;

  reg_read_data_1 <= reg_array(to_integer(unsigned(reg_read_addr_1)));
  reg_read_data_2 <= reg_array(to_integer(unsigned(reg_read_addr_2)));

end Behavioral;

tb/tb_register.vhd
library ieee;
use ieee.std_logic_1164.all;
use ieee.numeric_std.all;
use std.textio.all;
use ieee.std_logic_textio.all;   -- para hread

entity tb_register is
end entity;

architecture behavioral of tb_register is

  ------------------------------------------------------------------------------
  -- Component under test
  ------------------------------------------------------------------------------
  component register_file_VHDL
    port (
      clk            : in  std_logic;
      rst            : in  std_logic;
      reg_write_en   : in  std_logic;
      reg_write_dest : in  std_logic_vector(4 downto 0);
      reg_write_data : in  std_logic_vector(31 downto 0);
      reg_read_addr_1: in  std_logic_vector(4 downto 0);
      reg_read_data_1: out std_logic_vector(31 downto 0);
      reg_read_addr_2: in  std_logic_vector(4 downto 0);
      reg_read_data_2: out std_logic_vector(31 downto 0)
    );
  end component;

  ------------------------------------------------------------------------------
  -- Signals
  ------------------------------------------------------------------------------
  signal clk            : std_logic := '0';
  signal rst            : std_logic := '1';
  signal reg_write_en   : std_logic := '0';
  signal reg_write_dest : std_logic_vector(4 downto 0) := (others => '0');
  signal reg_write_data : std_logic_vector(31 downto 0) := (others => '0');
  signal reg_read_addr_1: std_logic_vector(4 downto 0) := (others => '0');
  signal reg_read_data_1: std_logic_vector(31 downto 0);
  signal reg_read_addr_2: std_logic_vector(4 downto 0) := (others => '0');
  signal reg_read_data_2: std_logic_vector(31 downto 0);

begin

  ------------------------------------------------------------------------------
  -- Clock generation
  ------------------------------------------------------------------------------
  clk <= not clk after 5 ns;

  ------------------------------------------------------------------------------
  -- Instantiate DUT
  ------------------------------------------------------------------------------
  uut: register_file_VHDL
    port map (
      clk             => clk,
      rst             => rst,
      reg_write_en    => reg_write_en,
      reg_write_dest  => reg_write_dest,
      reg_write_data  => reg_write_data,
      reg_read_addr_1 => reg_read_addr_1,
      reg_read_data_1 => reg_read_data_1,
      reg_read_addr_2 => reg_read_addr_2,
      reg_read_data_2 => reg_read_data_2
    );

  ------------------------------------------------------------------------------
  -- Stimulus process
  ------------------------------------------------------------------------------
  stim_proc : process
    file f        : text open read_mode is "tests/register.input";
    variable line_v : line;
    variable cmd_str : string(1 to 5);
    variable dest, addr1, addr2 : integer;
    variable data, expected1, expected2 : std_logic_vector(31 downto 0);
    variable test_count : integer := 0;
    variable error_count: integer := 0;
  begin
    -- Release reset
    wait for 20 ns;
    rst <= '0';

    while not endfile(f) loop
      readline(f, line_v);
      read(line_v, cmd_str);
      
      if cmd_str = "WRITE" then
        read(line_v, dest);
        hread(line_v, data);  -- lê valor hex
        reg_write_dest <= std_logic_vector(to_unsigned(dest,5));
        reg_write_data <= data;
        reg_write_en   <= '1';
        wait for 10 ns;
        reg_write_en   <= '0';
        test_count := test_count + 1;
        
      elsif cmd_str = "READ " then
        read(line_v, addr1);
        read(line_v, addr2);
        hread(line_v, expected1);
        hread(line_v, expected2);

        reg_read_addr_1 <= std_logic_vector(to_unsigned(addr1,5));
        reg_read_addr_2 <= std_logic_vector(to_unsigned(addr2,5));
        wait for 10 ns;

        test_count := test_count + 1;

        if reg_read_data_1 /= expected1 then
          report "ERRO: Test #" & integer'image(test_count) &
                 " addr1=" & integer'image(addr1) &
                 " esperado=" & to_hstring(expected1) &
                 " obtido=" & to_hstring(reg_read_data_1)
                 severity error;
          error_count := error_count + 1;
        else
          report "OK: Test #" & integer'image(test_count) &
                 " addr1=" & integer'image(addr1) &
                 " valor=" & to_hstring(reg_read_data_1)
                 severity note;
        end if;

        if reg_read_data_2 /= expected2 then
          report "ERRO: Test #" & integer'image(test_count) &
                 " addr2=" & integer'image(addr2) &
                 " esperado=" & to_hstring(expected2) &
                 " obtido=" & to_hstring(reg_read_data_2)
                 severity error;
          error_count := error_count + 1;
        else
          report "OK: Test #" & integer'image(test_count) &
                 " addr2=" & integer'image(addr2) &
                 " valor=" & to_hstring(reg_read_data_2)
                 severity note;
        end if;
      end if;

      wait for 10 ns;
    end loop;

    report "Simulação finalizada: " & integer'image(test_count) & " testes, " &
           integer'image(error_count) & " erros." severity note;

    wait;
  end process;

end architecture behavioral;

sim/register.vcd
$date
  Sat Nov 15 21:13:23 2025
$end
$version
  GHDL v0
$end
$timescale
  1 fs
$end
$scope module standard $end
$upscope $end
$scope module textio $end
$upscope $end
$scope module std_logic_1164 $end
$upscope $end
$scope module numeric_std $end
$upscope $end
$scope module std_logic_textio $end
$upscope $end
$scope module tb_register $end
$var reg 1 ! clk $end
$var reg 1 " rst $end
$var reg 1 # reg_write_en $end
$var reg 5 $ reg_write_dest[4:0] $end
$var reg 32 % reg_write_data[31:0] $end
$var reg 5 & reg_read_addr_1[4:0] $end
$var reg 32 ' reg_read_data_1[31:0] $end
$var reg 5 ( reg_read_addr_2[4:0] $end
$var reg 32 ) reg_read_data_2[31:0] $end
$scope module uut $end
$var reg 1 * clk $end
$var reg 1 + rst $end
$var reg 1 , reg_write_en $end
$var reg 5 - reg_write_dest[4:0] $end
$var reg 32 . reg_write_data[31:0] $end
$var reg 5 / reg_read_addr_1[4:0] $end
$var reg 32 0 reg_read_data_1[31:0] $end
$var reg 5 1 reg_read_addr_2[4:0] $end
$var reg 32 2 reg_read_data_2[31:0] $end
$comment reg_array is not handled $end
$upscope $end
$upscope $end
$enddefinitions $end
#0
0!
1"
0#
b00000 $
b00000000000000000000000000000000 %
b00000 &
b00000000000000000000000000000000 '
b00000 (
b00000000000000000000000000000000 )
0*
1+
0,
b00000 -
b00000000000000000000000000000000 .
b00000 /
b00000000000000000000000000000000 0
b00000 1
b00000000000000000000000000000000 2
#5000000
1!
1*
#10000000
0!
0*
#15000000
1!
1*
#20000000
0!
0"
1#
b00000000000000000000000000000001 %
0*
0+
1,
b00000000000000000000000000000001 .
#25000000
1!
b00000000000000000000000000000001 '
b00000000000000000000000000000001 )
1*
b00000000000000000000000000000001 0
b00000000000000000000000000000001 2
#30000000
0!
0#
0*
0,
#35000000
1!
1*
#40000000
0!
1#
b00001 $
b00000000000000000000000000000010 %
0*
1,
b00001 -
b00000000000000000000000000000010 .
#45000000
1!
1*
#50000000
0!
0#
0*
0,
#55000000
1!
1*
#60000000
0!
1#
b00010 $
b00010010001101000101011001111000 %
0*
1,
b00010 -
b00010010001101000101011001111000 .
#65000000
1!
1*
#70000000
0!
0#
0*
0,
#75000000
1!
1*
#80000000
0!
1#
b00011 $
b10101011110011011110111100000001 %
0*
1,
b00011 -
b10101011110011011110111100000001 .
#85000000
1!
1*
#90000000
0!
0#
0*
0,
#95000000
1!
1*
#100000000
0!
1#
b00100 $
b00001111000011110000111100001111 %
0*
1,
b00100 -
b00001111000011110000111100001111 .
#105000000
1!
1*
#110000000
0!
0#
0*
0,
#115000000
1!
1*
#120000000
0!
1#
b00101 $
b11110000111100001111000011110000 %
0*
1,
b00101 -
b11110000111100001111000011110000 .
#125000000
1!
1*
#130000000
0!
0#
0*
0,
#135000000
1!
1*
#140000000
0!
b00001 (
b00000000000000000000000000000010 )
0*
b00001 1
b00000000000000000000000000000010 2
#145000000
1!
1*
#150000000
0!
0*
#155000000
1!
1*
#160000000
0!
b00010 &
b00010010001101000101011001111000 '
b00011 (
b10101011110011011110111100000001 )
0*
b00010 /
b00010010001101000101011001111000 0
b00011 1
b10101011110011011110111100000001 2
#165000000
1!
1*
#170000000
0!
0*
#175000000
1!
1*
#180000000
0!
b00100 &
b00001111000011110000111100001111 '
b00101 (
b11110000111100001111000011110000 )
0*
b00100 /
b00001111000011110000111100001111 0
b00101 1
b11110000111100001111000011110000 2
#185000000
1!
1*
#190000000
0!
0*
#195000000
1!
1*
#200000000
0!
b00110 &
b00000000000000000000000000000000 '
b00111 (
b00000000000000000000000000000000 )
0*
b00110 /
b00000000000000000000000000000000 0
b00111 1
b00000000000000000000000000000000 2
